surfgen/__init__.py
surfgen/core.py
surfgen/math.py
surfgen/util.py
surfgen-0.2.8.dist-info/LICENSE
surfgen-0.2.8.dist-info/METADATA
surfgen-0.2.8.dist-info/WHEEL
surfgen-0.2.8.dist-info/top_level.txt
surfgen-0.2.8.dist-info/RECORD
