Metadata-Version: 2.1
Name: surfgen
Version: 0.2.8
Summary: Tools for creating slab models
Home-page: UNKNOWN
Author: Zheng-Da He
Author-email: z.he@fz-juelich.de, jameshzd@mail.ustc.edu.cn, zhengdahe.electrocatalysis@gmail.com
License: GPL-3.0
Platform: UNKNOWN
Requires: ase
Requires: pymatgen
